poetry_import/__init__.py
poetry_import/backport.py
poetry_import/command.py
poetry_import_plugin-3.0.1.dist-info/LICENSE
poetry_import_plugin-3.0.1.dist-info/METADATA
poetry_import_plugin-3.0.1.dist-info/WHEEL
poetry_import_plugin-3.0.1.dist-info/entry_points.txt
poetry_import_plugin-3.0.1.dist-info/RECORD
