Metadata-Version: 2.3
Name: poetry-import-plugin
Version: 3.0.1
Summary: Convert requirements.txt to pyproject.toml
License: Apache-2.0
Keywords: poetry,pyproject,toml,requirements,import
Author: Ben Chen
Author-email: benbenbang@github.com
Requires-Python: >=3.7,<4.0
Classifier: Development Status :: 5 - Production/Stable
Classifier: Intended Audience :: Developers
Classifier: Intended Audience :: Science/Research
Classifier: License :: OSI Approved :: Apache Software License
Classifier: Programming Language :: Python :: 3
Classifier: Programming Language :: Python :: 3.7
Classifier: Programming Language :: Python :: 3.8
Classifier: Programming Language :: Python :: 3.9
Classifier: Programming Language :: Python :: 3.10
Classifier: Programming Language :: Python :: 3.11
Classifier: Programming Language :: Python :: 3.12
Classifier: Programming Language :: Python :: 3.13
Project-URL: Repository, https://github.com/benbenbang/poetry-import-plugin
